setup.py
ethernetscan/__init__.py
ethernetscan/main.py
ethernetscan.egg-info/PKG-INFO
ethernetscan.egg-info/SOURCES.txt
ethernetscan.egg-info/dependency_links.txt
ethernetscan.egg-info/entry_points.txt
ethernetscan.egg-info/requires.txt
ethernetscan.egg-info/top_level.txt