Metadata-Version: 1.0
Name: ethernetscan
Version: 0.0.2
Summary: Scan Ethernet
Home-page: https://github.com/ipconfiger/etherscan
Author: Alexander.Li
Author-email: superpowerlee@gmail.com
License: GNU General Public License v3.0
Platform: UNKNOWN
